egrc_core/__init__.py
egrc_core/__version__.py
egrc_core/audit/__init__.py
egrc_core/audit/api.py
egrc_core/audit/middleware.py
egrc_core/audit/models.py
egrc_core/audit/processor.py
egrc_core/audit/schemas.py
egrc_core/audit/service.py
egrc_core/cache/__init__.py
egrc_core/cache/decorators.py
egrc_core/cache/models.py
egrc_core/cache/redis_client.py
egrc_core/cache/utils.py
egrc_core/cli/tenant_cli.py
egrc_core/cli.py
egrc_core/config/__init__.py
egrc_core/config/settings.py
egrc_core/constants/__init__.py
egrc_core/constants/constants.py
egrc_core/core/__init__.py
egrc_core/core/auth.py
egrc_core/core/global_id.py
egrc_core/core/tenant.py
egrc_core/core/types.py
egrc_core/crud/__init__.py
egrc_core/crud/base.py
egrc_core/crud/base_crud.py
egrc_core/crud/filters.py
egrc_core/crud/pagination.py
egrc_core/crud/repository.py
egrc_core/crud/sorting.py
egrc_core/database/__init__.py
egrc_core/database/base.py
egrc_core/database/database.py
egrc_core/database/declarative.py
egrc_core/database/tenant_manager.py
egrc_core/exceptions/__init__.py
egrc_core/exceptions/exceptions.py
egrc_core/graphql/__init__.py
egrc_core/graphql/example.py
egrc_core/graphql/filters.py
egrc_core/graphql/pagination.py
egrc_core/graphql/schema.py
egrc_core/graphql/schemas.py
egrc_core/graphql/sorting.py
egrc_core/llm/__init__.py
egrc_core/llm/models/__init__.py
egrc_core/llm/models/database.py
egrc_core/llm/models/schemas.py
egrc_core/llm/providers/__init__.py
egrc_core/llm/providers/anthropic.py
egrc_core/llm/providers/base.py
egrc_core/llm/providers/deepseek.py
egrc_core/llm/providers/factory.py
egrc_core/llm/providers/llama.py
egrc_core/llm/providers/openai.py
egrc_core/llm/services/__init__.py
egrc_core/llm/services/conversation_service.py
egrc_core/llm/services/llm_service.py
egrc_core/llm/services/usage_service.py
egrc_core/llm/utils/__init__.py
egrc_core/llm/utils/helpers.py
egrc_core/llm/utils/prompt_templates.py
egrc_core/llm/utils/text_processing.py
egrc_core/logging/__init__.py
egrc_core-1.3.0.dist-info/LICENSE
egrc_core-1.3.0.dist-info/METADATA
egrc_core-1.3.0.dist-info/WHEEL
egrc_core-1.3.0.dist-info/entry_points.txt
egrc_core-1.3.0.dist-info/RECORD
